[
    {
      "id": 0,
      "title": "Rottweiler",
      "filename": "gettyimages-4444-1024x1024.jpg"
    },
    {
      "id": 1,
      "title": "Gorilla",
      "filename": "gettyimages-85406425-1024x1024.jpg"
    },
    {
      "id": 2,
      "title": "Twins",
      "filename": "gettyimages-155157013-1024x1024.jpg"
    },
    {
      "id": 3,
      "title": "Man on Train",
      "filename": "gettyimages-156328094-1024x1024.jpg"
    },
    {
      "id": 4,
      "title": "Ocean Desk",
      "filename": "gettyimages-479631951-1024x1024.jpg"
    },
    {
      "id": 5,
      "title": "Man Playing Guitar",
      "filename": "gettyimages-951534490-1024x1024.jpg"
    }
]